domainprops/domainprops.py
domainprops-0.3.0.dist-info/LICENSE
domainprops-0.3.0.dist-info/WHEEL
domainprops-0.3.0.dist-info/METADATA
domainprops-0.3.0.dist-info/RECORD
