Metadata-Version: 2.1
Name: domainprops
Version: 0.3.0
Summary: Parse domain name properties.
Home-page: https://github.com/vikpe/domainprops
License: MIT
Keywords: domains,domain names,parse
Author: Viktor Persson
Author-email: viktor.persson@arcsin.se
Requires-Python: >=3.6,<4.0
Classifier: License :: OSI Approved :: MIT License
Classifier: Programming Language :: Python :: 3
Classifier: Programming Language :: Python :: 3.6
Classifier: Programming Language :: Python :: 3.7
Classifier: Programming Language :: Python :: 3.8
Classifier: Topic :: Internet
Classifier: Topic :: Utilities
Project-URL: Repository, https://github.com/vikpe/domainprops
